src/__init__.py
src/framegrab.py
ComCaveSnipper-0.0.1.dist-info/LICENSE
ComCaveSnipper-0.0.1.dist-info/METADATA
ComCaveSnipper-0.0.1.dist-info/WHEEL
ComCaveSnipper-0.0.1.dist-info/top_level.txt
ComCaveSnipper-0.0.1.dist-info/RECORD
