Metadata-Version: 2.1
Name: ComCaveSnipper
Version: 0.0.1
Summary: Auto insert PIN in ComeCave Launcher
Home-page: https://ginnie3112x@dev.azure.com/ginnie3112x/ComeCaveSnipper/_git/ComeCaveSnipper
Author: ginnie3112x
Author-email: ginnie3112x@gmail.com
License: UNKNOWN
Platform: UNKNOWN
Classifier: Programming Language :: Python :: 3
Classifier: License :: OSI Approved :: MIT License
Classifier: Operating System :: OS Independent
Requires-Python: >=3.7
